{
  "project_info": {
    "project_number": "873295341604",
    "project_id": "pdf-to-voice-app",
    "storage_bucket": "pdf-to-voice-app.firebasestorage.app"
  },
  "client": [
    {
      "client_info": {
        "mobilesdk_app_id": "1:873295341604:android:e4aeda90725291e0e4d0b1",
        "android_client_info": {
          "package_name": "com.example.pdftovoice"
        }
      },
      "oauth_client": [
        {
          "client_id": "873295341604-g1jqv8briuoavqf2ae8hc2gk9ilvp174.apps.googleusercontent.com",
          "client_type": 3
        }
      ],
      "api_key": [
        {
          "current_key": "AIzaSyAxu1QsBAcmUYJeBmSpyTZftPW4aYV4A2U"
        }
      ],
      "services": {
        "appinvite_service": {
          "other_platform_oauth_client": [
            {
              "client_id": "873295341604-g1jqv8briuoavqf2ae8hc2gk9ilvp174.apps.googleusercontent.com",
              "client_type": 3
            }
          ]
        }
      }
    }
  ],
  "configuration_version": "1"
}